<?xml version="1.0" ?><BarangInfo><Barang><owner><email>sedap@gmail.com</email><password>sedap123</password><NamaBadan>PT Sedap Indonesia</NamaBadan><NomorBadan>0-21-861-3045</NomorBadan><alamatBadan>Jl Madrasah I 11 RT 008/10, Dki Jakarta</alamatBadan><role>Seller</role></owner><namaproduk>Sedap Pedas</namaproduk><deskripsiproduk>Mie sedap ini sangat enak sekali untuk di makan bersamaan dengan telur dan juga sosis akan membuat bergairah dan lezat</deskripsiproduk><categoriproduk>Makanan</categoriproduk><expiredproduk>2023-07-31</expiredproduk><pengirimanproduk>jne,jnt,pickup,</pengirimanproduk><fotoproduk>Database/Barang/fotoProduct/Sedapmie.png</fotoproduk><stockproduk>320</stockproduk></Barang></BarangInfo>