<?xml version="1.0" ?><PesananInfo><Pesanan><pembeli><email>mifta</email><password>mifta</password><NamaBadan>mifta</NamaBadan><NomorBadan>081</NomorBadan><alamatBadan>jalan mifta</alamatBadan><role>Buyer</role></pembeli><product><owner><email>widyahelo123@gmail.com</email><password>widya123</password><NamaBadan>PT WIDYA</NamaBadan><NomorBadan>0825437689</NomorBadan><alamatBadan>DIAS KOST MUSLIM</alamatBadan><role>Seller</role></owner><namaproduk>sirup</namaproduk><deskripsiproduk>marjan</deskripsiproduk><categoriproduk>Minuman</categoriproduk><expiredproduk>2023-06-29</expiredproduk><pengirimanproduk>pickup,</pengirimanproduk><fotoproduk>Database/Barang/fotoProduct/sirupmiftah.png</fotoproduk><stockproduk>89</stockproduk></product><jumlahpesanan>29</jumlahpesanan><pengirimanpesanan>pickup</pengirimanpesanan><infopesanan>Menunggu Konfirmasi</infopesanan></Pesanan></PesananInfo>